psimpy/__init__.py
psimpy/emulator/__init__.py
psimpy/emulator/robustgasp.py
psimpy/inference/__init__.py
psimpy/inference/active_learning.py
psimpy/inference/bayes_inference.py
psimpy/sampler/__init__.py
psimpy/sampler/latin.py
psimpy/sampler/metropolis_hastings.py
psimpy/sampler/saltelli.py
psimpy/sensitivity/__init__.py
psimpy/sensitivity/sobol.py
psimpy/simulator/__init__.py
psimpy/simulator/mass_point_model.py
psimpy/simulator/ravaflow3G.py
psimpy/simulator/run_simulator.py
psimpy/utility/__init__.py
psimpy/utility/util_funcs.py
psimpy-1.0.1.dist-info/licenses/LICENSE
psimpy-1.0.1.dist-info/METADATA
psimpy-1.0.1.dist-info/WHEEL
psimpy-1.0.1.dist-info/RECORD
