Metadata-Version: 2.4
Name: psimpy
Version: 1.0.1
Summary: Predictive and probabilistic simulation tools.
License: MIT
License-File: LICENSE
Keywords: emulator,simulator,inference,sensitivity,uncertainty
Author: Hu Zhao
Requires-Python: >=3.9
Classifier: License :: OSI Approved :: MIT License
Classifier: Programming Language :: Python :: 3
Classifier: Programming Language :: Python :: 3.9
Classifier: Programming Language :: Python :: 3.10
Classifier: Programming Language :: Python :: 3.11
Classifier: Programming Language :: Python :: 3.12
Classifier: Programming Language :: Python :: 3.13
Classifier: Programming Language :: Python :: 3.14
Requires-Dist: SALib (>1.4.5)
Requires-Dist: beartype (>0.11.0)
Requires-Dist: numpy (>1.22.3,<2.4)
Requires-Dist: rpy2 (>3.5.1,<3.6)
Requires-Dist: scikit-learn (>=1.4.2,<2.0.0)
Requires-Dist: scipy (>1.10.0)
Project-URL: Homepage, https://git.rwth-aachen.de/mbd/psimpy
